
{"items":[{"name":"YouTube - 2015","href":"youtube-2015.html","topicHref":"youtube-2015.html","homepage":"youtube-2015.html"},{"name":"YouTube - 2016","href":"youtube-2016.html","topicHref":"youtube-2016.html","homepage":"youtube-2016.html"},{"name":"YouTube - 2017","href":"youtube-2017.html","topicHref":"youtube-2017.html","homepage":"youtube-2017.html"},{"name":"YouTube - 2018","href":"youtube-2018.html","topicHref":"youtube-2018.html","homepage":"youtube-2018.html"},{"name":"YouTube - 2020","href":"youtube-2020.html","topicHref":"youtube-2020.html","homepage":"youtube-2020.html"},{"name":"YouTube - 2021","href":"youtube-2021.html","topicHref":"youtube-2021.html","homepage":"youtube-2021.html"},{"name":"YouTube - 2022","href":"youtube-2022.html","topicHref":"youtube-2022.html","homepage":"youtube-2022.html"},{"name":"YouTube - 2023","href":"youtube-2023.html","topicHref":"youtube-2023.html","homepage":"youtube-2023.html"},{"name":"YouTube - 2024","href":"youtube-2024.html","topicHref":"youtube-2024.html","homepage":"youtube-2024.html"}]}
