
{"items":[{"name":"2010","href":"cbs-news-2010.html","topicHref":"cbs-news-2010.html","homepage":"cbs-news-2010.html"},{"name":"2016","href":"cbs-news-2016.html","topicHref":"cbs-news-2016.html","homepage":"cbs-news-2016.html"},{"name":"2017","href":"cbs-news-2017.html","topicHref":"cbs-news-2017.html","homepage":"cbs-news-2017.html"},{"name":"2019","href":"cbs-news-2019.html","topicHref":"cbs-news-2019.html","homepage":"cbs-news-2019.html"},{"name":"2023","href":"cbs-news-2023.html","topicHref":"cbs-news-2023.html","homepage":"cbs-news-2023.html"}]}