
{"items":[{"name":"2009","href":"the-guardian-2009.html","topicHref":"the-guardian-2009.html","homepage":"the-guardian-2009.html"},{"name":"2016","href":"the-guardian-2016.html","topicHref":"the-guardian-2016.html","homepage":"the-guardian-2016.html"},{"name":"2017","href":"the-guardian-2017.html","topicHref":"the-guardian-2017.html","homepage":"the-guardian-2017.html"},{"name":"2018","href":"the-guardian-2018.html","topicHref":"the-guardian-2018.html","homepage":"the-guardian-2018.html"},{"name":"2019","href":"the-guardian-2019.html","topicHref":"the-guardian-2019.html","homepage":"the-guardian-2019.html"},{"name":"2022","href":"the-guardian-2022.html","topicHref":"the-guardian-2022.html","homepage":"the-guardian-2022.html"}]}